{
	"$schema": "../../packages/data/schema/vessel.schema.json",
	"vessel": {
		"id": "hms-orion",
		"name": "HMS Orion",
		"country": "UK",
		"kind": "light-cruiser",
		"force": "G",
		"pennantNumber": "85",
		"displacement": 7215,
		"sources": ["roskill-1961"]
	},
	"track": {
		"vesselId": "hms-orion",
		"waypoints": [
			{
				"time": "1944-06-05T22:00:00Z",
				"position": [-0.55, 49.43],
				"sources": ["roskill-1961"],
				"note": "Bombarding Force K (Gold) station."
			},
			{
				"time": "1944-06-06T05:50:00Z",
				"position": [-0.55, 49.42],
				"sources": ["roskill-1961"],
				"note": "Opens 6-inch fire ; supports 50th Division advance through Asnelles and inland."
			},
			{
				"time": "1944-06-06T18:00:00Z",
				"position": [-0.55, 49.42],
				"sources": ["roskill-1961"],
				"note": "Continues call-fire."
			}
		]
	}
}
