{
	"$schema": "../packages/data/schema/frontline.schema.json",
	"segments": [
		{
			"id": "cotentin-airborne",
			"label": "US airborne pocket (Cotentin)",
			"closed": true,
			"sources": ["harrison-1951", "us-na-aar"],
			"keyframes": [
				{
					"time": "1944-06-06T02:30:00Z",
					"path": [
						[-1.36, 49.43],
						[-1.30, 49.44],
						[-1.26, 49.43],
						[-1.24, 49.40],
						[-1.26, 49.37],
						[-1.32, 49.36],
						[-1.36, 49.38],
						[-1.36, 49.43]
					]
				},
				{
					"time": "1944-06-06T06:30:00Z",
					"path": [
						[-1.40, 49.45],
						[-1.30, 49.45],
						[-1.20, 49.42],
						[-1.18, 49.39],
						[-1.20, 49.36],
						[-1.30, 49.34],
						[-1.38, 49.36],
						[-1.40, 49.45]
					]
				},
				{
					"time": "1944-06-06T12:00:00Z",
					"path": [
						[-1.40, 49.46],
						[-1.30, 49.46],
						[-1.16, 49.42],
						[-1.14, 49.36],
						[-1.20, 49.32],
						[-1.32, 49.31],
						[-1.42, 49.36],
						[-1.40, 49.46]
					]
				},
				{
					"time": "1944-06-06T18:00:00Z",
					"path": [
						[-1.42, 49.47],
						[-1.28, 49.47],
						[-1.14, 49.42],
						[-1.12, 49.34],
						[-1.22, 49.30],
						[-1.36, 49.30],
						[-1.44, 49.36],
						[-1.42, 49.47]
					]
				}
			]
		},
		{
			"id": "omaha-beachhead",
			"label": "Omaha beachhead front",
			"closed": false,
			"sources": ["harrison-1951", "us-na-aar"],
			"keyframes": [
				{
					"time": "1944-06-06T07:00:00Z",
					"path": [
						[-0.940, 49.380],
						[-0.910, 49.376],
						[-0.880, 49.374],
						[-0.870, 49.371],
						[-0.855, 49.369],
						[-0.835, 49.371]
					]
				},
				{
					"time": "1944-06-06T09:00:00Z",
					"path": [
						[-0.940, 49.378],
						[-0.910, 49.371],
						[-0.880, 49.369],
						[-0.870, 49.366],
						[-0.855, 49.364],
						[-0.835, 49.366]
					]
				},
				{
					"time": "1944-06-06T12:00:00Z",
					"path": [
						[-0.945, 49.374],
						[-0.915, 49.367],
						[-0.885, 49.362],
						[-0.870, 49.358],
						[-0.860, 49.355],
						[-0.835, 49.357]
					]
				},
				{
					"time": "1944-06-06T18:00:00Z",
					"path": [
						[-0.950, 49.368],
						[-0.920, 49.358],
						[-0.890, 49.353],
						[-0.875, 49.348],
						[-0.860, 49.346],
						[-0.835, 49.348]
					]
				}
			]
		},
		{
			"id": "utah-beachhead",
			"label": "Utah beachhead front",
			"closed": false,
			"sources": ["harrison-1951", "us-na-aar"],
			"keyframes": [
				{
					"time": "1944-06-06T07:00:00Z",
					"path": [
						[-1.18, 49.408],
						[-1.20, 49.395],
						[-1.21, 49.385],
						[-1.20, 49.376]
					]
				},
				{
					"time": "1944-06-06T12:00:00Z",
					"path": [
						[-1.23, 49.410],
						[-1.25, 49.395],
						[-1.27, 49.385],
						[-1.26, 49.375]
					]
				},
				{
					"time": "1944-06-06T18:00:00Z",
					"path": [
						[-1.26, 49.412],
						[-1.28, 49.395],
						[-1.30, 49.385],
						[-1.28, 49.372]
					]
				}
			]
		}
	]
}
